weblate_schemas/__init__.py
weblate_schemas/messages.py
weblate_schemas/py.typed
weblate_schemas/schemas/weblate-backup.schema.json
weblate_schemas/schemas/weblate-component.schema.json
weblate_schemas/schemas/weblate-memory.schema.json
weblate_schemas/schemas/weblate-messaging.schema.json
weblate_schemas/schemas/weblate-userdata.schema.json
weblate_schemas/tests/__init__.py
weblate_schemas/tests/test_loader.py
weblate_schemas/tests/test_message.py
weblate_schemas/tests/test_valid.py
weblate_schemas-2025.6.dist-info/licenses/LICENSE
weblate_schemas-2025.6.dist-info/METADATA
weblate_schemas-2025.6.dist-info/WHEEL
weblate_schemas-2025.6.dist-info/entry_points.txt
weblate_schemas-2025.6.dist-info/top_level.txt
weblate_schemas-2025.6.dist-info/RECORD
