Metadata-Version: 2.4
Name: weblate_schemas
Version: 2025.6
Summary: A collection of JSON schemas used by Weblate
Author-email: Michal Čihař <michal@weblate.org>
License-Expression: MIT
Project-URL: Documentation, https://docs.weblate.org/
Project-URL: Download, https://github.com/WeblateOrg/weblate_schemas
Project-URL: Funding, https://weblate.org/donate/
Project-URL: Homepage, https://weblate.org/
Project-URL: Issue Tracker, https://github.com/WeblateOrg/weblate_schemas/issues
Project-URL: Source Code, https://github.com/WeblateOrg/weblate_schemas
Project-URL: Twitter, https://twitter.com/WeblateOrg
Keywords: i18n,l10n,gettext,weblate,translate
Platform: any
Classifier: Development Status :: 5 - Production/Stable
Classifier: Intended Audience :: Developers
Classifier: Operating System :: OS Independent
Classifier: Programming Language :: Python
Classifier: Programming Language :: Python :: 3
Classifier: Programming Language :: Python :: 3 :: Only
Classifier: Programming Language :: Python :: 3.9
Classifier: Programming Language :: Python :: 3.10
Classifier: Programming Language :: Python :: 3.11
Classifier: Programming Language :: Python :: 3.12
Classifier: Programming Language :: Python :: 3.13
Classifier: Topic :: Software Development :: Internationalization
Classifier: Topic :: Software Development :: Localization
Classifier: Topic :: Utilities
Requires-Python: >=3.9
License-File: LICENSE
Requires-Dist: jsonschema[format]>=4.24.0
Provides-Extra: dev
Requires-Dist: weblate_schemas[lint,test]; extra == "dev"
Provides-Extra: lint
Requires-Dist: pre-commit==4.3.0; extra == "lint"
Provides-Extra: test
Requires-Dist: pytest; extra == "test"
Requires-Dist: pytest-cov; extra == "test"
Requires-Dist: fedora-messaging; extra == "test"
Requires-Dist: jsonschema[format]; extra == "test"
Dynamic: license-file
